verilog/Assignment2_mode_2/DFF_reset.v
module DFF_reset (
    input d,
    input clk,
    input reset,
    output q,
    output not_q
);
    reg q_reg;
    assign not_q = ~q_reg;

    always @(posedge clk) begin
        if (reset) q_reg <= 1'b0;
        else q_reg <= d;
    end
endmodule

verilog/Assignment2_mode_2/counter.v
module counter (
    input clk,
    input reset,
    input mode,
    output [2:0] count
);
    // Instantiate three D flip-flop modules
    DFF_reset dff1 (
        .d(carry_out),
        .clk(clk),
        .reset(reset),
        .q(count[0]),
        .not_q(not_q1)
    );
    DFF_reset dff2 (
        .d(mode ? not_q1 : carry_out),
        .clk(clk),
        .reset(reset),
        .q(count[1]),
        .not_q(not_q2)
    );
    DFF_reset dff3 (
        .d(mode ? not_q2 : carry_out),
        .clk(clk),
        .reset(reset),
        .q(count[2]),
        .not_q(not_q3)
    );
    // Output carry_o   ut is the inverse of the 3-bit count value
    assign carry_out = ~count;
endmodule

verilog/Assignment2_mode_2/counter_tb.v
module counter_tb;
    // Inputs
    reg clk;
    reg reset;
    reg mode;
    // Outputs
    wire [2:0] count;

    // Instantiate the counter under test
    counter uut (
        .clk(clk),
        .reset(reset),
        .mode(mode),
        .count(count)
    );

    // Test case 1: Count in binary mode from 0 to 7
    initial begin
        $dumpfile("counter_tb_mode_2.vcd");
        $dumpvars;
        reset = 1;
        #1 reset = 0;
        mode = 0;
        for (integer i = 0; i < 8; i++) begin
            #1 clk = 1;
            #1 clk = 0;
        end
    end

    // Test case 2: Count in gray code mode from 0 to 7
    initial begin
        reset = 1;
        #1 reset = 0;
        mode = 1;
        for (integer i = 0; i < 8; i++) begin
            #1 clk = 1;
            #1 clk = 0;
        end
    end
endmodule

verilog/Assignment2_mode_2/counter_tb_mode_2.vcd
$date
	Tue Dec 27 20:14:21 2022
$end
$version
	Icarus Verilog
$end
$timescale
	1s
$end
$scope module counter_tb $end
$var wire 3 ! count [2:0] $end
$var reg 1 " clk $end
$var reg 1 # mode $end
$var reg 1 $ reset $end
$scope module uut $end
$var wire 1 " clk $end
$var wire 1 # mode $end
$var wire 1 $ reset $end
$var wire 1 % not_q3 $end
$var wire 1 & not_q2 $end
$var wire 1 ' not_q1 $end
$var wire 3 ( count [2:0] $end
$var wire 1 ) carry_out $end
$scope module dff1 $end
$var wire 1 " clk $end
$var wire 1 ) d $end
$var wire 1 ' not_q $end
$var wire 1 * q $end
$var wire 1 $ reset $end
$var reg 1 + q_reg $end
$upscope $end
$scope module dff2 $end
$var wire 1 " clk $end
$var wire 1 , d $end
$var wire 1 & not_q $end
$var wire 1 - q $end
$var wire 1 $ reset $end
$var reg 1 . q_reg $end
$upscope $end
$scope module dff3 $end
$var wire 1 " clk $end
$var wire 1 / d $end
$var wire 1 % not_q $end
$var wire 1 0 q $end
$var wire 1 $ reset $end
$var reg 1 1 q_reg $end
$upscope $end
$upscope $end
$scope begin $ivl_for_loop0 $end
$var integer 32 2 i [31:0] $end
$upscope $end
$scope begin $ivl_for_loop1 $end
$var integer 32 3 i [31:0] $end
$upscope $end
$upscope $end
$enddefinitions $end
#0
$dumpvars
bx 3
bx 2
x1
z0
x/
x.
z-
x,
x+
z*
z)
bz (
x'
x&
x%
1$
x#
x"
bz !
$end
#1
b0 3
b0 2
1#
0$
#2
z+
1"
#3
b1 3
b1 2
0"
#4
1"
#5
b10 3
b10 2
0"
#6
1"
#7
b11 3
b11 2
0"
#8
1"
#9
b100 3
b100 2
0"
#10
1"
#11
b101 3
b101 2
0"
#12
1"
#13
b110 3
b110 2
0"
#14
1"
#15
b111 3
b111 2
0"
#16
1"
#17
b1000 3
b1000 2
0"
