bcd_to_7_seg_7448_decoder.v
module  bcd_to_7_seg_7448_decoder(A,B,C,D,a,b,c,d,e,f,g);
   input  A,B,C,D;
   output  a,b,c,d,e,f,g;

    assign a = (~B&~D)|(B&D) |A|(~B&C);
    assign b=~B|(~C&~D)|(C&D);
    assign c=~C|D|B;
    assign d=(~B&~D)|(~B&C)|(B&~C&D)|(C&~D);
    assign e=(~B&~D)|(C&~D);
    assign f=(~C&~D)|(B&~C)|(B&~D)|A;
    assign g=(~B&C)|(B&~C)|A|(C&~D);

endmodule

bcd_to_7_seg_7448_decoder_tb.v
`timescale 1ns/ 10ps
//`include "bcd_to_7_seg_7448_decoder.v"

module bcd_to_7_seg_7448_decoder_tb;
reg  A_in,B_in,C_in,D_in;
wire a_out,b_out,c_out,d_out,e_out,f_out,g_out;

bcd_to_7_seg_7448_decoder uut(A_in,B_in,C_in,D_in,a_out,b_out,c_out,d_out,e_out,f_out,g_out);
initial begin
   $dumpfile("bcd_to_7_seg_7448_decoder_tb.vcd");
   $dumpvars;
    A_in=0;
    B_in=0;
    C_in=0;
    D_in=0;
    #100;
    D_in=1;
    #100;
     A_in=0;
    B_in=0;
    C_in=1;
    D_in=0;
    #100;
    A_in=0;
    B_in=0;
    C_in=1;
    D_in=1;
    #100;
    A_in=0;
    B_in=1;
    C_in=0;
    D_in=0;
    #100;
    A_in=0;
    B_in=1;
    C_in=0;
    D_in=1;
    #100;
    A_in=0;
    B_in=1;
    C_in=1;
    D_in=0;
    #100;
    A_in=0;
    B_in=1;
    C_in=1;
    D_in=1;
    #100;
     A_in=1;
    B_in=0;
    C_in=0;
    D_in=0;
    #100;
     A_in=1;
    B_in=0;
    C_in=0;
    D_in=1;
    #100;
  
     $display("Test complete");
    $finish;
   
end
endmodule

verilog/others/bcd_to_7_seg_7448_decoder_tb.vcd
$date
	Thu Dec 08 21:41:28 2022
$end
$version
	Icarus Verilog
$end
$timescale
	10ps
$end
$scope module bcd_to_7_seg_7448_decoder_tb $end
$var wire 1 ! g_out $end
$var wire 1 " f_out $end
$var wire 1 # e_out $end
$var wire 1 $ d_out $end
$var wire 1 % c_out $end
$var wire 1 & b_out $end
$var wire 1 ' a_out $end
$var reg 1 ( A_in $end
$var reg 1 ) B_in $end
$var reg 1 * C_in $end
$var reg 1 + D_in $end
$scope module uut $end
$var wire 1 ( A $end
$var wire 1 ) B $end
$var wire 1 * C $end
$var wire 1 + D $end
$var wire 1 ' a $end
$var wire 1 & b $end
$var wire 1 % c $end
$var wire 1 $ d $end
$var wire 1 # e $end
$var wire 1 " f $end
$var wire 1 ! g $end
$upscope $end
$upscope $end
$enddefinitions $end
$comment Show the parameter values. $end
$dumpall
$end
#0
$dumpvars
0+
0*
0)
0(
1'
1&
1%
1$
1#
1"
0!
$end
#10000
0'
0$
0"
0#
1+
#20000
1$
1#
1!
0%
1'
0+
1*
#30000
0#
1%
1+
#40000
1"
0$
0'
1&
0+
0*
1)
#50000
1'
0&
1$
1+
#60000
0'
1#
0+
1*
#70000
1'
0"
0$
0#
0!
1&
1+
#80000
1$
1#
1!
1"
0+
0*
0)
1(
#90000
0$
0#
1+
